dftracer/__init__.py
dftracer/_version.py
dftracer/dftracer.cpython-311-x86_64-linux-gnu.so
dftracer/dftracer_dbg.cpython-311-x86_64-linux-gnu.so
dftracer/bin/dftracer_service
dftracer/bin/git_sparse_clone_interactive
dftracer/bin/git_sparse_push_interactive
dftracer/etc/modulefiles/brahma-2.3.0.lua
dftracer/etc/modulefiles/cpp-logger-1.1.0.lua
dftracer/etc/modulefiles/dftracer-4.0.0.lua
dftracer/include/brahma.h
dftracer/include/brahma/brahma.h
dftracer/include/brahma/brahma_config.hpp
dftracer/include/brahma/enumeration.h
dftracer/include/brahma/interceptor.h
dftracer/include/brahma/logging.h
dftracer/include/brahma/singleton.h
dftracer/include/brahma/interface/interface.h
dftracer/include/brahma/interface/interface_utility.h
dftracer/include/brahma/interface/posix.h
dftracer/include/brahma/interface/stdio.h
dftracer/include/cpp-logger/clogger.h
dftracer/include/cpp-logger/cpp_logger_config.hpp
dftracer/include/cpp-logger/logger.h
dftracer/include/dftracer/dftracer.h
dftracer/include/dftracer/core/dftracer_config.hpp
dftracer/include/dftracer/core/dftracer_config_dbg.hpp
dftracer/include/dftracer/core/common/constants.h
dftracer/include/dftracer/core/common/typedef.h
dftracer/include/gotcha/gotcha.h
dftracer/include/gotcha/gotcha_config.h
dftracer/include/gotcha/gotcha_types.h
dftracer/include/yaml-cpp/anchor.h
dftracer/include/yaml-cpp/binary.h
dftracer/include/yaml-cpp/dll.h
dftracer/include/yaml-cpp/emitfromevents.h
dftracer/include/yaml-cpp/emitter.h
dftracer/include/yaml-cpp/emitterdef.h
dftracer/include/yaml-cpp/emittermanip.h
dftracer/include/yaml-cpp/emitterstyle.h
dftracer/include/yaml-cpp/eventhandler.h
dftracer/include/yaml-cpp/exceptions.h
dftracer/include/yaml-cpp/mark.h
dftracer/include/yaml-cpp/null.h
dftracer/include/yaml-cpp/ostream_wrapper.h
dftracer/include/yaml-cpp/parser.h
dftracer/include/yaml-cpp/stlemitter.h
dftracer/include/yaml-cpp/traits.h
dftracer/include/yaml-cpp/yaml.h
dftracer-2.0.2.dist-info/METADATA
dftracer-2.0.2.dist-info/WHEEL
dftracer-2.0.2.dist-info/top_level.txt
dftracer-2.0.2.dist-info/RECORD
dftracer-2.0.2.dist-info/licenses/LICENSE
