Metadata-Version: 2.4
Name: dftracer
Version: 2.0.2
Summary: I/O profiler for deep learning python apps. Specifically for dlio_benchmark.
Author-email: "Hariharan Devarajan (Hari)" <hariharandev1@llnl.gov>
Project-URL: Homepage, https://github.com/LLNL/dftracer
Project-URL: Repository, https://github.com/LLNL/dftracer
Project-URL: Bug Tracker, https://github.com/LLNL/dftracer/issues
Project-URL: Documentation, https://dftracer.readthedocs.io/en/latest/
Keywords: profiler,deep learning,I/O,benchmark,NPZ,pytorch benchmark,tensorflow benchmark
Classifier: Development Status :: 3 - Alpha
Classifier: Intended Audience :: Science/Research
Classifier: Topic :: Software Development :: Build Tools
Classifier: License :: OSI Approved :: MIT License
Classifier: Programming Language :: Python :: 3.7
Classifier: Programming Language :: Python :: 3.8
Classifier: Programming Language :: Python :: 3.9
Classifier: Programming Language :: Python :: 3.10
Classifier: Programming Language :: Python :: 3 :: Only
Requires-Python: >=3.7
License-File: LICENSE
Requires-Dist: pybind11
Requires-Dist: setuptools>=64
Requires-Dist: setuptools-scm>=8
Requires-Dist: dftracer-utils>=0.0.5
Requires-Dist: pydftracer==2.0.2
Provides-Extra: test
Requires-Dist: pytest>=6.0; extra == "test"
Provides-Extra: dfanalyzer
Requires-Dist: dftracer-analyzer==0.0.2; extra == "dfanalyzer"
Provides-Extra: dfanalyzer-old
Requires-Dist: seaborn>=0.13.2; extra == "dfanalyzer-old"
Requires-Dist: bokeh>=2.4.2; extra == "dfanalyzer-old"
Requires-Dist: pybind11; extra == "dfanalyzer-old"
Requires-Dist: pandas>=2.0.3; extra == "dfanalyzer-old"
Requires-Dist: dask>=2023.5.0; extra == "dfanalyzer-old"
Requires-Dist: distributed; extra == "dfanalyzer-old"
Requires-Dist: numpy>=1.24.3; extra == "dfanalyzer-old"
Requires-Dist: pyarrow>=12.0.1; extra == "dfanalyzer-old"
Requires-Dist: rich>=13.6.0; extra == "dfanalyzer-old"
Requires-Dist: python-intervals>=1.10.0.post1; extra == "dfanalyzer-old"
Requires-Dist: matplotlib>=3.7.3; extra == "dfanalyzer-old"
Provides-Extra: dynamo
Requires-Dist: torch>=2.5.1; extra == "dynamo"
Dynamic: license-file
